passagemath_meataxe/__init__.py
passagemath_meataxe.libs/libmtx-cac93def.so.0.0.0
sage/all__sagemath_meataxe.py
sage/libs/all__sagemath_meataxe.py
sage/libs/meataxe.cpython-314t-x86_64-linux-gnu.so
sage/libs/meataxe.pxd
sage/libs/meataxe.pyx
sage/matrix/all__sagemath_meataxe.py
sage/matrix/matrix_gfpn_dense.cpython-314t-x86_64-linux-gnu.so
sage/matrix/matrix_gfpn_dense.pxd
sage/matrix/matrix_gfpn_dense.pyx
sage_wheels/share/meataxe/p002.zzz
sage_wheels/share/meataxe/p003.zzz
sage_wheels/share/meataxe/p004.zzz
sage_wheels/share/meataxe/p005.zzz
sage_wheels/share/meataxe/p007.zzz
sage_wheels/share/meataxe/p008.zzz
sage_wheels/share/meataxe/p009.zzz
sage_wheels/share/meataxe/p011.zzz
sage_wheels/share/meataxe/p013.zzz
sage_wheels/share/meataxe/p016.zzz
sage_wheels/share/meataxe/p017.zzz
sage_wheels/share/meataxe/p019.zzz
sage_wheels/share/meataxe/p023.zzz
sage_wheels/share/meataxe/p025.zzz
sage_wheels/share/meataxe/p027.zzz
sage_wheels/share/meataxe/p029.zzz
sage_wheels/share/meataxe/p031.zzz
sage_wheels/share/meataxe/p032.zzz
sage_wheels/share/meataxe/p037.zzz
sage_wheels/share/meataxe/p041.zzz
sage_wheels/share/meataxe/p043.zzz
sage_wheels/share/meataxe/p047.zzz
sage_wheels/share/meataxe/p049.zzz
sage_wheels/share/meataxe/p053.zzz
sage_wheels/share/meataxe/p059.zzz
sage_wheels/share/meataxe/p061.zzz
sage_wheels/share/meataxe/p064.zzz
sage_wheels/share/meataxe/p067.zzz
sage_wheels/share/meataxe/p071.zzz
sage_wheels/share/meataxe/p073.zzz
sage_wheels/share/meataxe/p079.zzz
sage_wheels/share/meataxe/p081.zzz
sage_wheels/share/meataxe/p083.zzz
sage_wheels/share/meataxe/p089.zzz
sage_wheels/share/meataxe/p097.zzz
sage_wheels/share/meataxe/p101.zzz
sage_wheels/share/meataxe/p103.zzz
sage_wheels/share/meataxe/p107.zzz
sage_wheels/share/meataxe/p109.zzz
sage_wheels/share/meataxe/p113.zzz
sage_wheels/share/meataxe/p121.zzz
sage_wheels/share/meataxe/p125.zzz
sage_wheels/share/meataxe/p127.zzz
passagemath_meataxe-10.6.43.dist-info/METADATA
passagemath_meataxe-10.6.43.dist-info/METADATA.bak
passagemath_meataxe-10.6.43.dist-info/WHEEL
passagemath_meataxe-10.6.43.dist-info/top_level.txt
passagemath_meataxe-10.6.43.dist-info/RECORD
